marshmallow_pageinfo/__init__.py
marshmallow_pageinfo-1.0.0.dist-info/LICENSE
marshmallow_pageinfo-1.0.0.dist-info/METADATA
marshmallow_pageinfo-1.0.0.dist-info/WHEEL
marshmallow_pageinfo-1.0.0.dist-info/top_level.txt
marshmallow_pageinfo-1.0.0.dist-info/RECORD
