Metadata-Version: 2.1
Name: marshmallow-pageinfo
Version: 1.0.0
Summary: Page info marshmallow schema for api
Home-page: UNKNOWN
Author: Dmitriy Pleshevskiy
Author-email: dmitriy@ideascup.me
License: MIT
Platform: UNKNOWN
